langchain_opengauss/__init__.py
langchain_opengauss/config.py
langchain_opengauss/openGaussAGEGraph.py
langchain_opengauss/opengauss.py
langchain_opengauss-0.1.4.dist-info/LICENSE
langchain_opengauss-0.1.4.dist-info/METADATA
langchain_opengauss-0.1.4.dist-info/WHEEL
langchain_opengauss-0.1.4.dist-info/RECORD
