Metadata-Version: 2.3
Name: langchain-opengauss
Version: 0.1.4
Summary: openGauss vector store integration for LangChain
License: MIT
Requires-Python: >=3.9,<4.0
Classifier: License :: OSI Approved :: MIT License
Classifier: Programming Language :: Python :: 3
Classifier: Programming Language :: Python :: 3.9
Classifier: Programming Language :: Python :: 3.10
Classifier: Programming Language :: Python :: 3.11
Classifier: Programming Language :: Python :: 3.12
Classifier: Programming Language :: Python :: 3.13
Requires-Dist: langchain-community (>=0.3.20)
Requires-Dist: langchain-core (>=0.2.13,<0.4.0)
Requires-Dist: psycopg2-binary (>=2.9.6)
Requires-Dist: pydantic (>=2.9.0)
Project-URL: Repository, https://github.com/mpb159753/langchain-opengauss
Project-URL: Source Code, https://github.com/mpb159753/langchain-opengauss
